switchtfi/__init__.py
switchtfi/data_processing.py
switchtfi/fit.py
switchtfi/plotting.py
switchtfi/pvalue_calculation.py
switchtfi/tf_ranking.py
switchtfi/utils.py
switchtfi/weight_fitting.py
switchtfi-0.1.0.dist-info/licenses/LICENSE
switchtfi-0.1.0.dist-info/METADATA
switchtfi-0.1.0.dist-info/WHEEL
switchtfi-0.1.0.dist-info/top_level.txt
switchtfi-0.1.0.dist-info/RECORD
