Metadata-Version: 2.4
Name: switchtfi
Version: 0.1.0
Summary: Implementation of the SwitchTFI method as presented in: https://doi.org/10.1101/2025.01.20.633856
Author-email: Paul Martini <paul.martini@fau.de>
License:                     GNU GENERAL PUBLIC LICENSE
Project-URL: Source, https://github.com/bionetslab/SwitchTFI
Project-URL: Documentation, https://github.com/bionetslab/SwitchTFI#readme
Project-URL: Issues, https://github.com/bionetslab/SwitchTFI/issues
Keywords: bioinformatics,single-cell,gene-regulation,network-analysis
Classifier: Development Status :: 3 - Alpha
Classifier: Intended Audience :: Science/Research
Classifier: Topic :: Scientific/Engineering :: Bio-Informatics
Classifier: License :: OSI Approved :: GNU General Public License v3 (GPLv3)
Classifier: Programming Language :: Python :: 3
Classifier: Programming Language :: Python :: 3.9
Classifier: Programming Language :: Python :: 3.10
Classifier: Programming Language :: Python :: 3.11
Classifier: Programming Language :: Python :: 3.12
Requires-Python: <3.13,>=3.9
License-File: LICENSE
Requires-Dist: numpy>=1.26.4
Requires-Dist: pandas>=2.2.3
Requires-Dist: scipy>=1.14.1
Requires-Dist: scikit-learn>=1.5.2
Requires-Dist: statsmodels>=0.14.1
Requires-Dist: matplotlib>=3.5.2
Requires-Dist: seaborn>=0.13.2
Requires-Dist: anndata>=0.10.7
Requires-Dist: scanpy>=1.9.3
Requires-Dist: igraph>=0.11.4
Requires-Dist: magic-impute>=3.0.0
Requires-Dist: leidenalg>=0.10.2
Requires-Dist: networkx>=3.4
Dynamic: license-file
